userstory8020/__init__.py
userstory8020/__main__.py
userstory8020/app.py
userstory8020/factory.py
userstory8020/logging_conf.yml
userstory8020/process.json
userstory8020/scripts.py
userstory8020-0.0.42.dist-info/METADATA
userstory8020-0.0.42.dist-info/WHEEL
userstory8020-0.0.42.dist-info/entry_points.txt
userstory8020-0.0.42.dist-info/top_level.txt
userstory8020-0.0.42.dist-info/RECORD
