Metadata-Version: 2.1
Name: userstory8020
Version: 0.0.42
Summary: test assignment
Author-email: Mykola Kis <sikalokym@gmail.com>
Requires-Dist: pyspark ==3.4.1
Requires-Dist: pandas ==1.3.5
Requires-Dist: pyarrow ==12.0.1
Requires-Dist: grpcio ==1.57.0
Requires-Dist: google ==3.0.0
Requires-Dist: google-api-core ==2.11.1
Requires-Dist: grpcio-status ==1.57.0
Requires-Dist: PyYAML ==6.0.1
